github_listener
