Metadata-Version: 1.1
Name: github-listener
Version: 0.1.3
Summary: The simple library that calls user's registered functions whenever github events happen. (ex, notification)
Home-page: https://github.com/taeguk/github_listener
Author: taeguk
Author-email: xornrbboy@gmail.com
License: MIT
Keywords: github notification
Platform: UNKNOWN
Classifier: Programming Language :: Python :: 3 :: Only
